setup.py
dankapi_py/__init__.py
dankapi_py.egg-info/PKG-INFO
dankapi_py.egg-info/SOURCES.txt
dankapi_py.egg-info/dependency_links.txt
dankapi_py.egg-info/requires.txt
dankapi_py.egg-info/top_level.txt