Metadata-Version: 1.1
Name: dankapi-py
Version: 0.0.1
Summary: An easy to use, async ready Python Wrapper for the API DankAPI (https://dankapi.github.io).
Home-page: https://github.com/dankapi/dankapi_py
Author: Nimit Grover
Author-email: dankapi420@gmail.com
License: MIT
Keywords: apiwrapper dankmemer dankmemer-sale dankmemer-api api internet
Platform: UNKNOWN
Classifier: Development Status :: 5 - Production/Stable
Classifier: Intended Audience :: Developers
Classifier: Operating System :: OS Independent
Classifier: License :: OSI Approved :: MIT License
Classifier: Programming Language :: Python :: 3.9
